spacy_annotator/__init__.py
spacy_annotator-2.1.3.dist-info/METADATA
spacy_annotator-2.1.3.dist-info/WHEEL
spacy_annotator-2.1.3.dist-info/top_level.txt
spacy_annotator-2.1.3.dist-info/RECORD
