Metadata-Version: 2.1
Name: spacy-annotator
Version: 2.1.3
Summary: SpaCy annotator for Named Entity Recognition (NER) using ipywidgets.
Home-page: https://github.com/ieriii/spacy-annotator
Author: Enrico Alemani
Author-email: enrico.alemani@hey.com
License: MIT
Keywords: spacy,NER,NLP
Platform: UNKNOWN
